bidsphysio.events-21.6.24-py3.8-nspkg.pth
bidsphysio/events/__init__.py
bidsphysio/events/eventsbase.py
bidsphysio/events/info.py
tests/__init__.py
tests/test_eventsbase.py
tests/utils.py
bidsphysio.events-21.6.24.dist-info/METADATA
bidsphysio.events-21.6.24.dist-info/WHEEL
bidsphysio.events-21.6.24.dist-info/namespace_packages.txt
bidsphysio.events-21.6.24.dist-info/top_level.txt
bidsphysio.events-21.6.24.dist-info/RECORD
